pydantic_cloud/__init__.py
pydantic_cloud/gcp.py
pydantic_cloud_settings-0.0.5.dist-info/LICENSE.txt
pydantic_cloud_settings-0.0.5.dist-info/METADATA
pydantic_cloud_settings-0.0.5.dist-info/WHEEL
pydantic_cloud_settings-0.0.5.dist-info/top_level.txt
pydantic_cloud_settings-0.0.5.dist-info/RECORD
